app/__init__.py
app/models.py
app/urls.py
app/wsgi.py
app/migrations/0001_initial.py
app/migrations/0002_create_homepage.py
app/migrations/0003_auto_20220202_1235.py
app/migrations/__init__.py
app/settings/__init__.py
app/settings/base.py
app/settings/dev.py
app/settings/production.py
app/tests/__init__.py
app/tests/test_checkup.py
wagtail_metrics/__init__.py
wagtail_metrics/checkup.py
wagtail_metrics/constants.py
wagtail_metrics/exceptions.py
wagtail_metrics/metric.py
wagtail_metrics/providers/__init__.py
wagtail_metrics/providers/google_page_speed.py
wagtail_metrics/providers/request.py
wagtail_metrics/providers/wagtail_page.py
wagtail_metrics-0.0.11.dist-info/LICENSE
wagtail_metrics-0.0.11.dist-info/METADATA
wagtail_metrics-0.0.11.dist-info/WHEEL
wagtail_metrics-0.0.11.dist-info/top_level.txt
wagtail_metrics-0.0.11.dist-info/RECORD
