Metadata-Version: 2.1
Name: wagtail-metrics
Version: 0.0.11
Summary: Wagtail Metrics
Home-page: https://github.com/Aleksi44/wagtail-metrics
Author: Alexis Le Baron
Author-email: hello@snoweb.io
License: GPL-3.0
Keywords: wagtail metrics
Platform: linux
Classifier: Environment :: Web Environment
Classifier: Intended Audience :: Developers
Classifier: Programming Language :: Python
Classifier: Programming Language :: Python :: 3
Classifier: Programming Language :: Python :: 3.6
Classifier: Programming Language :: Python :: 3.7
Classifier: Programming Language :: Python :: 3.8
Classifier: Operating System :: OS Independent
Classifier: Topic :: Software Development
Classifier: Framework :: Wagtail :: 2
License-File: LICENSE
